{"name":"Battle-chat","tagline":"Unofficial chat application for Battlelog","body":"Battle Chat\r\n=============\r\nBattle Chat is an unofficial Battlelog chat [application for Android devices running 2.2+ and onward] (https://play.google.com/store/apps/details?id=com.ninetwozero.battlechat).\r\n\r\nAbout the author\r\n------------\r\n**Karl Lindmark**<br />\r\nE-mail: support@ninetwozero.com<br />\r\nWeb: http://www.ninetwozero.com<br />\r\nTwitter: [@karllindmark](https://www.twitter.com/karllindmark)<br />\r\n\r\nContributors\r\n------------\r\n**Peter Budo** (Maven & CI testing setup)<br />\r\nE-mail: peter.budo@gmail.com<br />\r\nTwitter: [@peter_budo](https://www.twitter.com/peter-budo)<br />\r\n\r\n**Daniel Peukert** (Czech translation)<br />\r\nTwitter: [@dapil](https://www.twitter.com/dapil)<br />\r\nWeb: http://gplus.to/dpeukert<br />\r\n\r\n**Steve Beaudet** (Logo)<br />\r\nTwitter: [@dbagjones](https://www.twitter.com/dbagjones)<br />\r\nWeb: http://djonesradio.com<br />\r\n\r\n\r\n### Special thanks\r\nTo all the people that have helped out by testing, providing feedback and/or anything else helpful. Much appreciated. :-)\r\n","google":"","note":"Don't delete this file! It's used internally to help with page regeneration."}